heynoterm/__init__.py
heynoterm/app.py
heynoterm/block.py
heynoterm/components.py
heynoterm/heynoterm.tcss
heynoterm/math_evaluator.py
heynoterm/state.py
heynoterm-0.2.1.dist-info/METADATA
heynoterm-0.2.1.dist-info/WHEEL
heynoterm-0.2.1.dist-info/entry_points.txt
heynoterm-0.2.1.dist-info/RECORD
