Metadata-Version: 2.4
Name: heynoterm
Version: 0.2.1
Author-email: Mehdi Ghodsizadeh <mehdi.ghodsizadeh@gmail.com>
Classifier: Environment :: Console
Classifier: Programming Language :: Python :: 3.10
Classifier: Programming Language :: Python :: 3.11
Classifier: Programming Language :: Python :: 3.12
Classifier: Topic :: Software Development :: User Interfaces
Requires-Python: >=3.10
Requires-Dist: textual-dev>=1.3.0
Requires-Dist: textual[syntax]>=0.46.0
Provides-Extra: dev
Requires-Dist: mypy>=1.8.0; extra == 'dev'
Requires-Dist: pre-commit>=3.6.0; extra == 'dev'
Requires-Dist: ruff>=0.1.9; extra == 'dev'
